README.md
setup.py
target_matcher/__init__.py
target_matcher/concept_tagger.py
target_matcher/target_matcher.py
target_matcher/target_rule.py
target_matcher.egg-info/PKG-INFO
target_matcher.egg-info/SOURCES.txt
target_matcher.egg-info/dependency_links.txt
target_matcher.egg-info/requires.txt
target_matcher.egg-info/top_level.txt