Metadata-Version: 2.1
Name: target-matcher
Version: 0.0.1
Summary: A wrapper class for extended rule-based matching in spaCy.
Home-page: UNKNOWN
Author: medSpaCy
Author-email: medspacy.dev@gmail.com
License: UNKNOWN
Platform: UNKNOWN
